regnorm/__init__.py
regnorm/main
regnorm/vinorm.py
regnorm/Dict/Popular.txt
regnorm/Mapping/Acronyms.txt
regnorm/Mapping/Acronyms_shorten.txt
regnorm/Mapping/BaseUnit.txt
regnorm/Mapping/CurrencyUnit.txt
regnorm/Mapping/LetterSoundEN.txt
regnorm/Mapping/LetterSoundVN.txt
regnorm/Mapping/Number.txt
regnorm/Mapping/PrefixUnit.txt
regnorm/Mapping/Symbol.txt
regnorm/Mapping/Teencode.txt
regnorm/RegexRule/Codenumber.txt
regnorm/RegexRule/Date_1.txt
regnorm/RegexRule/Date_2.txt
regnorm/RegexRule/Date_3.txt
regnorm/RegexRule/Date_From_To_1.txt
regnorm/RegexRule/Date_From_To_2.txt
regnorm/RegexRule/Email.txt
regnorm/RegexRule/FootballOther.txt
regnorm/RegexRule/FootballUnder.txt
regnorm/RegexRule/Measurement.txt
regnorm/RegexRule/Measurement_1.txt
regnorm/RegexRule/Month.txt
regnorm/RegexRule/NormalNumber.txt
regnorm/RegexRule/Office.txt
regnorm/RegexRule/PhoneNumber.txt
regnorm/RegexRule/PoliticalDivision.txt
regnorm/RegexRule/RomanNumber.txt
regnorm/RegexRule/Street.txt
regnorm/RegexRule/Time.txt
regnorm/RegexRule/Website.txt
regnorm/lib/libicudata.so
regnorm/lib/libicudata.so.64
regnorm/lib/libicudata.so.64.2
regnorm/lib/libicui18n.so
regnorm/lib/libicui18n.so.64
regnorm/lib/libicui18n.so.64.2
regnorm/lib/libicuio.so
regnorm/lib/libicuio.so.64
regnorm/lib/libicuio.so.64.2
regnorm/lib/libicutest.so
regnorm/lib/libicutest.so.64
regnorm/lib/libicutest.so.64.2
regnorm/lib/libicutu.so
regnorm/lib/libicutu.so.64
regnorm/lib/libicutu.so.64.2
regnorm/lib/libicuuc.so
regnorm/lib/libicuuc.so.64
regnorm/lib/libicuuc.so.64.2
regnorm/lib/icu/64.2/Makefile.inc
regnorm/lib/icu/64.2/pkgdata.inc
regnorm/lib/pkgconfig/icu-i18n.pc
regnorm/lib/pkgconfig/icu-io.pc
regnorm/lib/pkgconfig/icu-uc.pc
vinorm/__init__.py
vinorm/input.txt
vinorm/main
vinorm/output.txt
vinorm/vinorm.py
vinorm/Dict/Popular.txt
vinorm/Mapping/Acronyms.txt
vinorm/Mapping/Acronyms_shorten.txt
vinorm/Mapping/BaseUnit.txt
vinorm/Mapping/CurrencyUnit.txt
vinorm/Mapping/LetterSoundEN.txt
vinorm/Mapping/LetterSoundVN.txt
regnorm-0.0.4.dist-info/LICENSE
regnorm-0.0.4.dist-info/METADATA
regnorm-0.0.4.dist-info/WHEEL
regnorm-0.0.4.dist-info/top_level.txt
regnorm-0.0.4.dist-info/RECORD
