Metadata-Version: 2.1
Name: regnorm
Version: 0.0.4
Summary: Python package for text normalization, use for frontend of Text-to-speech Reseach
Home-page: UNKNOWN
License: UNKNOWN
Platform: UNKNOWN
Classifier: Development Status :: 4 - Beta
Classifier: License :: Free for non-commercial use
Classifier: Natural Language :: Vietnamese
Classifier: Operating System :: POSIX :: Linux
Classifier: Programming Language :: C++
Classifier: Programming Language :: Python :: 3.6
Classifier: Topic :: Scientific/Engineering :: Artificial Intelligence
License-File: LICENSE
